setup.py
audio_preprocessing/__init__.py
audio_preprocessing/preprocessing.py
audio_preprocessing.egg-info/PKG-INFO
audio_preprocessing.egg-info/SOURCES.txt
audio_preprocessing.egg-info/dependency_links.txt
audio_preprocessing.egg-info/not-zip-safe
audio_preprocessing.egg-info/top_level.txt