Metadata-Version: 1.0
Name: audio-preprocessing
Version: 0.1
Summary: audio_preprocessing
Home-page: UNKNOWN
Author: Shweta Yadav
Author-email: datascientist.shweta@gmail.com
License: UNKNOWN
Platform: UNKNOWN
